niceplots/__init__.py
niceplots/parula.py
niceplots/utils.py
niceplots/fonts/Prompt-Black.ttf
niceplots/fonts/Prompt-BlackItalic.ttf
niceplots/fonts/Prompt-Bold.ttf
niceplots/fonts/Prompt-BoldItalic.ttf
niceplots/fonts/Prompt-ExtraBold.ttf
niceplots/fonts/Prompt-ExtraBoldItalic.ttf
niceplots/fonts/Prompt-ExtraLight.ttf
niceplots/fonts/Prompt-ExtraLightItalic.ttf
niceplots/fonts/Prompt-Italic.ttf
niceplots/fonts/Prompt-Light.ttf
niceplots/fonts/Prompt-LightItalic.ttf
niceplots/fonts/Prompt-Medium.ttf
niceplots/fonts/Prompt-MediumItalic.ttf
niceplots/fonts/Prompt-Regular.ttf
niceplots/fonts/Prompt-SemiBold.ttf
niceplots/fonts/Prompt-SemiBoldItalic.ttf
niceplots/fonts/Prompt-Thin.ttf
niceplots/fonts/Prompt-ThinItalic.ttf
niceplots/fonts/cmb10.ttf
niceplots/fonts/cmbsy10.ttf
niceplots/fonts/cmbsy6.ttf
niceplots/fonts/cmbsy7.ttf
niceplots/fonts/cmbsy8.ttf
niceplots/fonts/cmbsy9.ttf
niceplots/fonts/cmbx10.ttf
niceplots/fonts/cmbx12.ttf
niceplots/fonts/cmbx5.ttf
niceplots/fonts/cmbx6.ttf
niceplots/fonts/cmbx7.ttf
niceplots/fonts/cmbx8.ttf
niceplots/fonts/cmbx9.ttf
niceplots/fonts/cmbxsl10.ttf
niceplots/fonts/cmbxti10.ttf
niceplots/fonts/cmcsc10.ttf
niceplots/fonts/cmcsc8.ttf
niceplots/fonts/cmcsc9.ttf
niceplots/fonts/cmdunh10.ttf
niceplots/fonts/cmex10.ttf
niceplots/fonts/cmex7.ttf
niceplots/fonts/cmex8.ttf
niceplots/fonts/cmex9.ttf
niceplots/fonts/cmff10.ttf
niceplots/fonts/cmfi10.ttf
niceplots/fonts/cmfib8.ttf
niceplots/fonts/cminch.ttf
niceplots/fonts/cmitt10.ttf
niceplots/fonts/cmmi10.ttf
niceplots/fonts/cmmi12.ttf
niceplots/fonts/cmmi5.ttf
niceplots/fonts/cmmi6.ttf
niceplots/fonts/cmmi7.ttf
niceplots/fonts/cmmi8.ttf
niceplots/fonts/cmmi9.ttf
niceplots/fonts/cmmib10.ttf
niceplots/fonts/cmmib6.ttf
niceplots/fonts/cmmib7.ttf
niceplots/fonts/cmmib8.ttf
niceplots/fonts/cmmib9.ttf
niceplots/fonts/cmr10.ttf
niceplots/fonts/cmr12.ttf
niceplots/fonts/cmr17.ttf
niceplots/fonts/cmr5.ttf
niceplots/fonts/cmr6.ttf
niceplots/fonts/cmr7.ttf
niceplots/fonts/cmr8.ttf
niceplots-2.6.1.dist-info/METADATA
niceplots-2.6.1.dist-info/WHEEL
niceplots-2.6.1.dist-info/top_level.txt
niceplots-2.6.1.dist-info/RECORD
