Metadata-Version: 2.1
Name: niceplots
Version: 2.6.1
Summary: Plotting utilities for matplotlib in python
Home-page: https://github.com/mdolab/niceplots
Author: 
Author-email: 
License: Apache License, Version 2.0
Platform: UNKNOWN
Requires-Dist: numpy>=1.21
Requires-Dist: matplotlib>=2.2
Requires-Dist: scipy>=1.7
